{
  "exchanges": [
    {
      "timestamp": "2026-03-30T00:43:04.956Z",
      "request": {
        "method": "POST",
        "path": "/ISAPI/AccessControl/AcsEvent?format=json",
        "url": "http://192.168.0.179/ISAPI/AccessControl/AcsEvent?format=json",
        "headers": {
          "accept": "application/json, application/xml, text/xml, text/plain, */*",
          "content-type": "application/json; charset=UTF-8"
        },
        "contentType": "application/json; charset=UTF-8",
        "bodyText": "{\"AcsEventCond\":{\"searchID\":\"acs-1774831384955\",\"searchResultPosition\":0,\"maxResults\":20,\"major\":5,\"minor\":75,\"startTime\":\"2026-03-30T00:38:03Z\",\"endTime\":\"2026-03-30T00:43:03Z\"}}",
        "bodyBytes": 179
      },
      "response": {
        "status": 401,
        "statusText": "Unauthorized",
        "headers": {
          "connection": "keep-alive",
          "content-length": "195",
          "content-type": "application/json",
          "date": "Mon, 30 Mar 2026 00:54:52 GMT",
          "keep-alive": "timeout=5, max=99",
          "referrer-policy": "no-referrer",
          "www-authenticate": "Digest qop=\"auth\", realm=\"DS-1315c7ab\", nonce=\"MmNkOTFlNmNmOGE4ODMxMjIwMmFiZTM3MTc0NDY1ZDc=\", stale=\"false\", opaque=\"\", domain=\"::\"",
          "x-content-type-options": "nosniff",
          "x-frame-options": "SAMEORIGIN",
          "x-xss-protection": "1; mode=block"
        },
        "contentType": "application/json",
        "bodyBytes": 195,
        "bodyText": "<userCheck version=\"2.0\" xmlns=\"http://www.isapi.org/ver20/XMLSchema\">\r\n<statusValue>401</statusValue>\r\n<statusString>Unauthorized</statusString>\r\n<isActivated>false</isActivated>\r\n</userCheck>\r\n"
      }
    },
    {
      "timestamp": "2026-03-30T00:43:05.004Z",
      "request": {
        "method": "POST",
        "path": "/ISAPI/AccessControl/AcsEvent?format=json",
        "url": "http://192.168.0.179/ISAPI/AccessControl/AcsEvent?format=json",
        "headers": {
          "accept": "application/json, application/xml, text/xml, text/plain, */*",
          "authorization": "***redacted***",
          "content-type": "application/json; charset=UTF-8"
        },
        "contentType": "application/json; charset=UTF-8",
        "bodyText": "{\"AcsEventCond\":{\"searchID\":\"acs-1774831384955\",\"searchResultPosition\":0,\"maxResults\":20,\"major\":5,\"minor\":75,\"startTime\":\"2026-03-30T00:38:03Z\",\"endTime\":\"2026-03-30T00:43:03Z\"}}",
        "bodyBytes": 179
      },
      "response": {
        "status": 200,
        "statusText": "OK",
        "headers": {
          "connection": "keep-alive",
          "content-length": "133",
          "content-type": "application/json",
          "date": "Mon, 30 Mar 2026 00:54:52 GMT",
          "keep-alive": "timeout=5, max=99",
          "referrer-policy": "no-referrer",
          "x-content-type-options": "nosniff",
          "x-frame-options": "SAMEORIGIN",
          "x-xss-protection": "1; mode=block"
        },
        "contentType": "application/json",
        "bodyBytes": 133,
        "bodyText": "{\n\t\"AcsEvent\":\t{\n\t\t\"searchID\":\t\"acs-1774831384955\",\n\t\t\"totalMatches\":\t0,\n\t\t\"responseStatusStrg\":\t\"NO MATCH\",\n\t\t\"numOfMatches\":\t0\n\t}\n}"
      }
    },
    {
      "timestamp": "2026-03-30T00:43:05.058Z",
      "request": {
        "method": "POST",
        "path": "/ISAPI/AccessControl/AcsEvent?format=json",
        "url": "http://192.168.0.179/ISAPI/AccessControl/AcsEvent?format=json",
        "headers": {
          "accept": "application/json, application/xml, text/xml, text/plain, */*",
          "content-type": "application/json; charset=UTF-8"
        },
        "contentType": "application/json; charset=UTF-8",
        "bodyText": "{\"AcsEventCond\":{\"searchID\":\"acs-1774831385057\",\"searchResultPosition\":0,\"maxResults\":20,\"major\":5,\"minor\":21,\"startTime\":\"2026-03-30T00:38:03Z\",\"endTime\":\"2026-03-30T00:43:03Z\"}}",
        "bodyBytes": 179
      },
      "response": {
        "status": 401,
        "statusText": "Unauthorized",
        "headers": {
          "connection": "keep-alive",
          "content-length": "195",
          "content-type": "application/json",
          "date": "Mon, 30 Mar 2026 00:54:52 GMT",
          "keep-alive": "timeout=5, max=98",
          "referrer-policy": "no-referrer",
          "www-authenticate": "Digest qop=\"auth\", realm=\"DS-1315c7ab\", nonce=\"ZTU2OTgyODE2NDI3ZTA3YjU3OTdjYTBmNGQwMDFjYTE=\", stale=\"false\", opaque=\"\", domain=\"::\"",
          "x-content-type-options": "nosniff",
          "x-frame-options": "SAMEORIGIN",
          "x-xss-protection": "1; mode=block"
        },
        "contentType": "application/json",
        "bodyBytes": 195,
        "bodyText": "<userCheck version=\"2.0\" xmlns=\"http://www.isapi.org/ver20/XMLSchema\">\r\n<statusValue>401</statusValue>\r\n<statusString>Unauthorized</statusString>\r\n<isActivated>false</isActivated>\r\n</userCheck>\r\n"
      }
    },
    {
      "timestamp": "2026-03-30T00:43:05.075Z",
      "request": {
        "method": "POST",
        "path": "/ISAPI/AccessControl/AcsEvent?format=json",
        "url": "http://192.168.0.179/ISAPI/AccessControl/AcsEvent?format=json",
        "headers": {
          "accept": "application/json, application/xml, text/xml, text/plain, */*",
          "authorization": "***redacted***",
          "content-type": "application/json; charset=UTF-8"
        },
        "contentType": "application/json; charset=UTF-8",
        "bodyText": "{\"AcsEventCond\":{\"searchID\":\"acs-1774831385057\",\"searchResultPosition\":0,\"maxResults\":20,\"major\":5,\"minor\":21,\"startTime\":\"2026-03-30T00:38:03Z\",\"endTime\":\"2026-03-30T00:43:03Z\"}}",
        "bodyBytes": 179
      },
      "response": {
        "status": 200,
        "statusText": "OK",
        "headers": {
          "connection": "keep-alive",
          "content-length": "133",
          "content-type": "application/json",
          "date": "Mon, 30 Mar 2026 00:54:52 GMT",
          "keep-alive": "timeout=5, max=98",
          "referrer-policy": "no-referrer",
          "x-content-type-options": "nosniff",
          "x-frame-options": "SAMEORIGIN",
          "x-xss-protection": "1; mode=block"
        },
        "contentType": "application/json",
        "bodyBytes": 133,
        "bodyText": "{\n\t\"AcsEvent\":\t{\n\t\t\"searchID\":\t\"acs-1774831385057\",\n\t\t\"totalMatches\":\t0,\n\t\t\"responseStatusStrg\":\t\"NO MATCH\",\n\t\t\"numOfMatches\":\t0\n\t}\n}"
      }
    },
    {
      "timestamp": "2026-03-30T00:43:05.099Z",
      "request": {
        "method": "POST",
        "path": "/ISAPI/AccessControl/AcsEvent?format=json",
        "url": "http://192.168.0.179/ISAPI/AccessControl/AcsEvent?format=json",
        "headers": {
          "accept": "application/json, application/xml, text/xml, text/plain, */*",
          "content-type": "application/json; charset=UTF-8"
        },
        "contentType": "application/json; charset=UTF-8",
        "bodyText": "{\"AcsEventCond\":{\"searchID\":\"acs-1774831385098\",\"searchResultPosition\":0,\"maxResults\":20,\"major\":5,\"minor\":22,\"startTime\":\"2026-03-30T00:38:03Z\",\"endTime\":\"2026-03-30T00:43:03Z\"}}",
        "bodyBytes": 179
      },
      "response": {
        "status": 401,
        "statusText": "Unauthorized",
        "headers": {
          "connection": "keep-alive",
          "content-length": "195",
          "content-type": "application/json",
          "date": "Mon, 30 Mar 2026 00:54:52 GMT",
          "keep-alive": "timeout=5, max=97",
          "referrer-policy": "no-referrer",
          "www-authenticate": "Digest qop=\"auth\", realm=\"DS-1315c7ab\", nonce=\"OTRhMjJmNGYxOGIyMDM2N2I2NzRkOWFlYzhjNjE4MjM=\", stale=\"false\", opaque=\"\", domain=\"::\"",
          "x-content-type-options": "nosniff",
          "x-frame-options": "SAMEORIGIN",
          "x-xss-protection": "1; mode=block"
        },
        "contentType": "application/json",
        "bodyBytes": 195,
        "bodyText": "<userCheck version=\"2.0\" xmlns=\"http://www.isapi.org/ver20/XMLSchema\">\r\n<statusValue>401</statusValue>\r\n<statusString>Unauthorized</statusString>\r\n<isActivated>false</isActivated>\r\n</userCheck>\r\n"
      }
    },
    {
      "timestamp": "2026-03-30T00:43:05.124Z",
      "request": {
        "method": "POST",
        "path": "/ISAPI/AccessControl/AcsEvent?format=json",
        "url": "http://192.168.0.179/ISAPI/AccessControl/AcsEvent?format=json",
        "headers": {
          "accept": "application/json, application/xml, text/xml, text/plain, */*",
          "authorization": "***redacted***",
          "content-type": "application/json; charset=UTF-8"
        },
        "contentType": "application/json; charset=UTF-8",
        "bodyText": "{\"AcsEventCond\":{\"searchID\":\"acs-1774831385098\",\"searchResultPosition\":0,\"maxResults\":20,\"major\":5,\"minor\":22,\"startTime\":\"2026-03-30T00:38:03Z\",\"endTime\":\"2026-03-30T00:43:03Z\"}}",
        "bodyBytes": 179
      },
      "response": {
        "status": 200,
        "statusText": "OK",
        "headers": {
          "connection": "keep-alive",
          "content-length": "133",
          "content-type": "application/json",
          "date": "Mon, 30 Mar 2026 00:54:52 GMT",
          "keep-alive": "timeout=5, max=97",
          "referrer-policy": "no-referrer",
          "x-content-type-options": "nosniff",
          "x-frame-options": "SAMEORIGIN",
          "x-xss-protection": "1; mode=block"
        },
        "contentType": "application/json",
        "bodyBytes": 133,
        "bodyText": "{\n\t\"AcsEvent\":\t{\n\t\t\"searchID\":\t\"acs-1774831385098\",\n\t\t\"totalMatches\":\t0,\n\t\t\"responseStatusStrg\":\t\"NO MATCH\",\n\t\t\"numOfMatches\":\t0\n\t}\n}"
      }
    }
  ]
}